{
    "51003970566_0.3521824351385374": {
        "condition": [],
        "commands": [
            [
                [
                    0,
                    1,
                    0,
                    [
                        0,
                        1,
                        1,
                        0
                    ],
                    0,
                    0,
                    [
                        0,
                        1,
                        1,
                        0
                    ],
                    1,
                    [
                        1,
                        15006,
                        [
                            0,
                            0
                        ]
                    ],
                    0,
                    0,
                    [
                        1,
                        1
                    ],
                    "",
                    "",
                    true,
                    null,
                    null,
                    null,
                    null,
                    null,
                    null,
                    0,
                    {
                        "___cmdID": "51004454898_0.6903424903141413"
                    }
                ],
                [
                    13,
                    4,
                    15006,
                    0,
                    0,
                    0,
                    1,
                    1,
                    [
                        0,
                        100
                    ],
                    0,
                    -1,
                    [],
                    0,
                    0,
                    0,
                    {
                        "___cmdID": "51004454898_0.31245315794857254"
                    }
                ],
                [
                    50001,
                    {
                        "51004823216_0.7870287660533613": false
                    },
                    "51004876783_0.5945612777744016"
                ],
                [
                    1,
                    {
                        "___cmdID": "51004454898_0.4618934037057809"
                    }
                ],
                [
                    13,
                    4,
                    15006,
                    0,
                    0,
                    1,
                    1,
                    1,
                    [
                        0,
                        100
                    ],
                    0,
                    -1,
                    [],
                    0,
                    0,
                    0,
                    {
                        "___cmdID": "51004454898_0.21373841680792238"
                    }
                ],
                [
                    50001,
                    {
                        "51004823216_0.7870287660533613": true
                    },
                    "51004878418_0.16421541774914572"
                ],
                [
                    2,
                    {
                        "___cmdID": "51004454898_0.4914502726183485"
                    }
                ]
            ],
            [],
            [],
            [],
            [],
            [],
            [],
            [],
            [],
            [],
            [],
            []
        ]
    },
    "51693436802_0.14734056462439038": {
        "condition": [],
        "commands": [
            [],
            [],
            [],
            [],
            [],
            [],
            [],
            [],
            [],
            [],
            [],
            []
        ]
    },
    "root": {
        "commands": [
            [
                [
                    -1,
                    {
                        "___cmdID": "126584856104_0.5845157869104698"
                    }
                ]
            ],
            [],
            [],
            [
                [
                    0,
                    5,
                    0,
                    [
                        0,
                        1,
                        1,
                        0
                    ],
                    0,
                    0,
                    [
                        0,
                        1,
                        1,
                        0
                    ],
                    0,
                    [
                        1,
                        1,
                        [
                            0,
                            0
                        ]
                    ],
                    0,
                    0,
                    [
                        1,
                        1
                    ],
                    "",
                    "",
                    true,
                    null,
                    [
                        5,
                        {
                            "sys": 3
                        },
                        [
                            {
                                "50994129090_0.9145624693624452": 3
                            }
                        ]
                    ],
                    null,
                    null,
                    null,
                    null,
                    0,
                    {
                        "___cmdID": "87893436112_0.26086633687076977"
                    }
                ],
                [
                    13,
                    4,
                    15006,
                    0,
                    0,
                    1,
                    1,
                    1,
                    [
                        0,
                        100
                    ],
                    0,
                    -1,
                    [],
                    0,
                    0,
                    0,
                    {
                        "___cmdID": "87893436112_0.6945564740760191"
                    }
                ],
                [
                    -1,
                    {
                        "___cmdID": "87893436112_0.3683056446305941"
                    }
                ],
                [
                    1,
                    {
                        "___cmdID": "87893436112_0.5145277381766142"
                    }
                ],
                [
                    13,
                    4,
                    15006,
                    0,
                    0,
                    0,
                    1,
                    1,
                    [
                        0,
                        100
                    ],
                    0,
                    -1,
                    [],
                    0,
                    0,
                    0,
                    {
                        "___cmdID": "87893436112_0.7999050650542854"
                    }
                ],
                [
                    -1,
                    {
                        "___cmdID": "87893436112_0.4097486084285933"
                    }
                ],
                [
                    2,
                    {
                        "___cmdID": "87893436112_0.8098715810192658"
                    }
                ],
                [
                    -1,
                    {
                        "___cmdID": "87893433689_0.1125489134170492"
                    }
                ]
            ],
            [],
            [],
            [],
            [],
            [],
            [],
            [],
            []
        ]
    },
    "77057147563_0.6605757976293434": {
        "condition": [],
        "commands": [
            [
                [
                    -1,
                    {
                        "___cmdID": "126585039377_0.35561032005490656"
                    }
                ]
            ],
            [],
            [],
            [],
            [],
            [],
            [],
            [],
            [],
            [],
            [],
            []
        ]
    },
    "86846568768_0.708502651241663": {
        "condition": [],
        "commands": [
            [
                [
                    -1,
                    {
                        "___cmdID": "126584809782_0.6883035856437072"
                    }
                ]
            ],
            [],
            [],
            [],
            [],
            [],
            [],
            [],
            [],
            [],
            [],
            []
        ]
    },
    "126584890917_0.9678893696000017": {
        "condition": [],
        "commands": [
            [
                [
                    60005,
                    {
                        "74577032484_0.13493609495640202": "asset/audio/se/menu/Return_Left.mp3,1,1",
                        "74578579319_0.15291120828407134": 1,
                        "91116691228_0.19588751423957396": 2,
                        "91116362027_0.0524615397494288": true,
                        "74587606222_0.5579985331498136": false
                    },
                    "126585103086_0.4301768591726216"
                ],
                [
                    16,
                    15004,
                    false,
                    {
                        "___cmdID": "126585103086_0.8944397639457293"
                    }
                ],
                [
                    -1,
                    {
                        "___cmdID": "126585094841_0.7717287133422512"
                    }
                ]
            ],
            [],
            [],
            [],
            [],
            [],
            [],
            [],
            [],
            [],
            [],
            []
        ]
    },
    "126662546366_0.7896280753985143": {
        "condition": [],
        "commands": [
            [],
            [],
            [],
            [],
            [],
            [],
            [],
            [],
            [],
            [],
            [],
            []
        ]
    },
    "126662546367_0.2809299158292955": {
        "condition": [],
        "commands": [
            [],
            [],
            [],
            [],
            [],
            [],
            [],
            [],
            [],
            [],
            [],
            []
        ]
    },
    "126662546367_0.35456047534929147": {
        "condition": [],
        "commands": [
            [
                [
                    60005,
                    {
                        "74577032484_0.13493609495640202": "asset/audio/se/menu/Return_Left.mp3,1,1",
                        "74578579319_0.15291120828407134": 1,
                        "91116691228_0.19588751423957396": 2,
                        "91116362027_0.0524615397494288": true,
                        "74587606222_0.5579985331498136": false
                    },
                    "126585482163_0.6261387369030218"
                ],
                [
                    16,
                    15004,
                    false,
                    {
                        "___cmdID": "126585482163_0.9909848989516254"
                    }
                ],
                [
                    -1,
                    {
                        "___cmdID": "126574956721_0.5123121547460883"
                    }
                ]
            ],
            [],
            [],
            [],
            [],
            [],
            [],
            [],
            [],
            [],
            [],
            []
        ]
    },
    "126662546367_0.2511079746326348": {
        "condition": [],
        "commands": [
            [
                [
                    -1,
                    {
                        "___cmdID": "126573655299_0.4349686569062905"
                    }
                ]
            ],
            [],
            [],
            [],
            [],
            [],
            [],
            [],
            [],
            [],
            [],
            []
        ]
    },
    "126662546367_0.6354818009459051": {
        "condition": [],
        "commands": [
            [
                [
                    60005,
                    {
                        "74577032484_0.13493609495640202": "asset/audio/se/menu/Return_Left.mp3,1,1",
                        "74578579319_0.15291120828407134": 1,
                        "91116691228_0.19588751423957396": 2,
                        "91116362027_0.0524615397494288": true,
                        "74587606222_0.5579985331498136": false
                    },
                    "126662596510_0.7910260010904637"
                ],
                [
                    16,
                    15004,
                    false,
                    {
                        "___cmdID": "126662596510_0.17635486789661536"
                    }
                ],
                [
                    -1,
                    {
                        "___cmdID": "126575023795_0.6831591531671368"
                    }
                ]
            ],
            [],
            [],
            [],
            [],
            [],
            [],
            [],
            [],
            [],
            [],
            []
        ]
    },
    "126662546367_0.8543979192032856": {
        "condition": [],
        "commands": [
            [
                [
                    -1,
                    {
                        "___cmdID": "126575023270_0.4093613809926504"
                    }
                ]
            ],
            [],
            [],
            [],
            [],
            [],
            [],
            [],
            [],
            [],
            [],
            []
        ]
    },
    "126662546368_0.011166401812812587": {
        "condition": [],
        "commands": [
            [],
            [],
            [],
            [],
            [],
            [],
            [],
            [],
            [],
            [],
            [],
            []
        ]
    },
    "126662546368_0.5132743831101478": {
        "condition": [],
        "commands": [
            [],
            [],
            [],
            [],
            [],
            [],
            [],
            [],
            [],
            [],
            [],
            []
        ]
    }
}